{
    "description": "The dangers that can be encountered while travelling the world.",
    "massiveInuries": {
        "description": "When suffering damage equal or greater than half your maximum [HP] or when you are reduced to 0 [HP] the first time in combat you suffer a massive Injuriy which usually has a more permanent effect. To determine your Injury roll a d100 and add all the excess damage then determine your Injury in the Table below (either all damage above half your maximum [HP] or all exceess damage beyond 0 [HP]).",
        "massiveInjuriesTable": [
            { "diceRoll": "01-20", "Injury": "Scar" },
            { "diceRoll": "21-40", "Injury": "Broken Bone" },
            { "diceRoll": "41-60", "Injury": "" },
            { "diceRoll": "61-80", "Injury": "" },
            { "diceRoll": "81-90", "Injury": "" },
            { "diceRoll": "91-100", "Injury": "" },
            { "diceRoll": "101-110", "Injury": "" },
            { "diceRoll": "111-120", "Injury": "" },
            { "diceRoll": "120+", "Injury": "" }
        ]
    },
    "fallingAndCrashingIntoObjects": {
        "description": "For every 4 meters a creature falls dawn they receive physical damage depending on their size (see table below) which can’t be reduced by armor. After 400 meters this damage does not increase any further. To determine how much a creature accelerates while falling down you can consult the Table below. This assumes that the creature doesn't slow down, additionally after turn 5 they don't accelarate further.",
        "fallingCreatureAccelerationTable": [
            {"truns": 1, "metersFallenThisTurn": 10, "totalDistanceFallen": 10},
            {"truns": 2, "metersFallenThisTurn": 50, "totalDistanceFallen": 60},
            {"truns": 3, "metersFallenThisTurn": 100, "totalDistanceFallen": 160},
            {"truns": 4, "metersFallenThisTurn": 200, "totalDistanceFallen": 360},
            {"truns": 5, "metersFallenThisTurn": 300, "totalDistanceFallen": 760}
        ],
        "cashingIntoOtherCreaturesDescription": "If a creature or object crashes into another creature the creature that is crashed into also recieves damage which depends on the Size of the creature that is crashing into it and how much that creature moved.",
        "creatureSizeFallDamage": [
            {"size": "Tiny", "physicalDamagePer4MentersMoved": "1"},
            {"size": "Small", "physicalDamagePer4MentersMoved": "1d4"},
            {"size": "Medium", "physicalDamagePer4MentersMoved": "1d6"},
            {"size": "Large", "physicalDamagePer4MentersMoved": "1d8"},
            {"size": "Huge", "physicalDamagePer4MentersMoved": "1d10"},
            {"size": "Gargantuan", "physicalDamagePer4MentersMoved": "1d12"},
            {"size": "Titanic", "physicalDamagePer4MentersMoved": "1d20"}
        ]
    },
    "traps": {
        "description": "TODO, mostly general rules for detecting and disarming traps"
    },
    "suffocatingAndDrowning": {
        "description": "TOOD, how long can hold breath, should do damage when out of breath, rules for loosing air when recieving damage"
    },
    "environmentalConditions": {
        "description": "",
        "extremeCold": {
            "description": "TODO, what effects, damage, what severity and how much cold resistance to overcome it"
        },
        "extremeHeat": {
            "description": "TODO, what effects, damage, what severity and how much fire resistance to overcome it"
        }
    },
    "poisonsAndDiseases": {
        "description": "TODO"
    }
}