{
  "folder": "ZxnQVja45syIC6Wf",
  "name": "Thick Winter Clothes",
  "type": "equipment",
  "_id": "gbojSzDKzawFBod8",
  "img": "icons/equipment/head/hood-leather-fur-brown.webp",
  "system": {
    "description": "<p>These winter clothes will keep you comfortable in Cold Temperatures and come with a cloak that can be woarn over armor. While wearing these clothes you gain Frost Resistance 1, but you cannot wear these clothes in Temperatures over 15°.</p>",
    "tier": 2,
    "type": "wearables",
    "costBc": 400,
    "quantity": 1,
    "weightKg": 4,
    "weightGramm": 0,
    "totalWeightGramm": 0,
    "recoverable": false,
    "damageBlock": 0,
    "manoeuvrePenalty": 0,
    "movementPenalty": 0,
    "shieldBlock": 0,
    "damageThreshold": 0,
    "craftingSkills": "Tailor's Sets"
  },
  "effects": [],
  "sort": 0,
  "ownership": {
    "default": 0,
    "dMcHPOGHbwLGpLCS": 3
  },
  "flags": {},
  "_stats": {
    "compendiumSource": null,
    "duplicateSource": null,
    "exportSource": null,
    "coreVersion": "13.345",
    "systemId": "reclaim-the-realm",
    "systemVersion": "2.0.0",
    "createdTime": 1750355440171,
    "modifiedTime": 1750355584161,
    "lastModifiedBy": "dMcHPOGHbwLGpLCS"
  },
  "_key": "!items!gbojSzDKzawFBod8"
}
